MANIFEST.in
README.txt
setup.cfg
setup.py
docs/HISTORY.txt
horae/__init__.py
horae.attachments.egg-info/PKG-INFO
horae.attachments.egg-info/SOURCES.txt
horae.attachments.egg-info/dependency_links.txt
horae.attachments.egg-info/entry_points.txt
horae.attachments.egg-info/namespace_packages.txt
horae.attachments.egg-info/not-zip-safe
horae.attachments.egg-info/requires.txt
horae.attachments.egg-info/top_level.txt
horae/attachments/__init__.py
horae/attachments/attachments.py
horae/attachments/configure.zcml
horae/attachments/extenders.py
horae/attachments/interfaces.py
horae/attachments/views.py
horae/attachments/locales/horae.attachments.pot
horae/attachments/locales/de/LC_MESSAGES/horae.attachments.mo
horae/attachments/locales/de/LC_MESSAGES/horae.attachments.po